Metadata-Version: 2.1
Name: Ogem-distributions
Version: 0.1
Summary: Gaussian and Binomial distributions
